main.py
mereview-1.0.4.dist-info/METADATA
mereview-1.0.4.dist-info/WHEEL
mereview-1.0.4.dist-info/entry_points.txt
mereview-1.0.4.dist-info/top_level.txt
mereview-1.0.4.dist-info/RECORD
