Metadata-Version: 2.4
Name: mereview
Version: 1.0.4
Summary: A CLI tool for reviewing coding assignments and Jupyter notebooks with AI-powered analysis
Author: Your Name
Author-email: destifo <estifanosbireda@gmail.com>
License: MIT
Project-URL: Homepage, https://github.com/yourusername/mereview
Project-URL: Repository, https://github.com/yourusername/mereview
Project-URL: Issues, https://github.com/yourusername/mereview/issues
Keywords: code-review,jupyter,notebook,ai,cli
Classifier: Development Status :: 4 - Beta
Classifier: Intended Audience :: Developers
Classifier: Intended Audience :: Education
Classifier: License :: OSI Approved :: MIT License
Classifier: Programming Language :: Python :: 3
Classifier: Programming Language :: Python :: 3.8
Classifier: Programming Language :: Python :: 3.9
Classifier: Programming Language :: Python :: 3.10
Classifier: Programming Language :: Python :: 3.11
Classifier: Programming Language :: Python :: 3.12
Classifier: Topic :: Software Development :: Quality Assurance
Classifier: Topic :: Education
Requires-Python: >=3.8
Requires-Dist: click>=8.1.0
Requires-Dist: requests>=2.31.0
Requires-Dist: nbformat>=5.9.0
Requires-Dist: nbconvert>=7.9.0
Requires-Dist: google-generativeai>=0.3.0
Dynamic: author
Dynamic: requires-python
